{"esm_exports":[{"exported_name":"ProfileCard","is_default":false,"kind":"declaration","local_name":"ProfileCard","source_path":"src/ProfileCard.tsx","span":{"end_column":1,"end_line":8,"start_column":7,"start_line":4}},{"exported_name":"loadProfile","is_default":false,"kind":"declaration","local_name":"loadProfile","source_path":"src/api.ts","span":{"end_column":1,"end_line":6,"start_column":7,"start_line":3}}],"esm_imports":[{"imported_name":"useEffect","kind":"named","local_name":"useEffect","module":"react","source_path":"src/ProfileCard.tsx","span":{"end_column":18,"end_line":1,"start_column":9,"start_line":1}},{"imported_name":"useState","kind":"named","local_name":"useState","module":"react","source_path":"src/ProfileCard.tsx","span":{"end_column":28,"end_line":1,"start_column":20,"start_line":1}},{"imported_name":"loadProfile","kind":"named","local_name":"loadProfile","module":"./api","source_path":"src/ProfileCard.tsx","span":{"end_column":20,"end_line":2,"start_column":9,"start_line":2}}],"extractor_diagnostics":[],"graph":{"edges":[{"confidence":1.0,"evidence_kind":"syntax_direct","relation":"contains","source_id":"directory:e6976e5c4a4414bc970c","source_path":"src/api.ts","target_id":"file:2f980a2d5f2ef251f26f"},{"confidence":1.0,"evidence_kind":"syntax_direct","relation":"contains","source_id":"directory:e6976e5c4a4414bc970c","source_path":"src/ProfileCard.tsx","target_id":"file:6e8b35ce6ddb90d60aa4"},{"confidence":1.0,"evidence_kind":"syntax_direct","relation":"contains","source_id":"file:2f980a2d5f2ef251f26f","source_path":"src/api.ts","span":{"end_column":0,"end_line":7,"start_column":0,"start_line":1},"target_id":"module:c08ac179146125b2d961"},{"confidence":1.0,"evidence_kind":"syntax_direct","relation":"contains","source_id":"file:6e8b35ce6ddb90d60aa4","source_path":"src/ProfileCard.tsx","span":{"end_column":0,"end_line":9,"start_column":0,"start_line":1},"target_id":"module:ad2d1756563bfcf3e988"},{"confidence":1.0,"evidence_kind":"syntax_direct","relation":"contains","source_id":"module:ad2d1756563bfcf3e988","source_path":"src/ProfileCard.tsx","span":{"end_column":1,"end_line":8,"start_column":7,"start_line":4},"target_id":"react_component:7fdeb1a9a312ef4e91ae"},{"confidence":1.0,"evidence_kind":"syntax_direct","relation":"contains","source_id":"module:c08ac179146125b2d961","source_path":"src/api.ts","span":{"end_column":1,"end_line":6,"start_column":7,"start_line":3},"target_id":"function:d2674e99f4b2e1a06fbc"},{"confidence":1.0,"evidence_kind":"syntax_direct","relation":"contains","source_id":"module:c08ac179146125b2d961","source_path":"src/api.ts","span":{"end_column":51,"end_line":1,"start_column":7,"start_line":1},"target_id":"type_alias:3b87916d8d5292ae8a93"},{"confidence":1.0,"evidence_kind":"syntax_direct","relation":"contains","source_id":"repository:a474b071e4f472328e16","source_path":"src","target_id":"directory:e6976e5c4a4414bc970c"},{"confidence":1.0,"evidence_kind":"syntax_direct","relation":"contains","source_id":"repository:a474b071e4f472328e16","source_path":"tsconfig.json","target_id":"file:0083e53b5ee9b5284942"}],"metadata":{},"nodes":[{"id":"directory:e6976e5c4a4414bc970c","kind":"directory","label":"src","metadata":{},"source_path":"src"},{"id":"file:0083e53b5ee9b5284942","kind":"file","label":"tsconfig.json","metadata":{"size_bytes":72,"suffix":".json"},"source_path":"tsconfig.json"},{"id":"file:2f980a2d5f2ef251f26f","kind":"file","label":"api.ts","language":"typescript","metadata":{"size_bytes":222,"suffix":".ts"},"source_path":"src/api.ts"},{"id":"file:6e8b35ce6ddb90d60aa4","kind":"file","label":"ProfileCard.tsx","language":"tsx","metadata":{"size_bytes":334,"suffix":".tsx"},"source_path":"src/ProfileCard.tsx"},{"id":"function:d2674e99f4b2e1a06fbc","kind":"function","label":"loadProfile","language":"typescript","metadata":{},"qualified_name":"src.api.loadProfile","source_path":"src/api.ts","span":{"end_column":1,"end_line":6,"start_column":7,"start_line":3}},{"id":"module:ad2d1756563bfcf3e988","kind":"module","label":"src.ProfileCard","language":"tsx","metadata":{},"qualified_name":"src.ProfileCard","source_path":"src/ProfileCard.tsx","span":{"end_column":0,"end_line":9,"start_column":0,"start_line":1}},{"id":"module:c08ac179146125b2d961","kind":"module","label":"src.api","language":"typescript","metadata":{},"qualified_name":"src.api","source_path":"src/api.ts","span":{"end_column":0,"end_line":7,"start_column":0,"start_line":1}},{"id":"react_component:7fdeb1a9a312ef4e91ae","kind":"react_component","label":"ProfileCard","language":"tsx","metadata":{},"qualified_name":"src.ProfileCard.ProfileCard","source_path":"src/ProfileCard.tsx","span":{"end_column":1,"end_line":8,"start_column":7,"start_line":4}},{"id":"repository:a474b071e4f472328e16","kind":"repository","label":"<repository>","metadata":{},"qualified_name":"<repository>","source_path":"."},{"id":"type_alias:3b87916d8d5292ae8a93","kind":"type_alias","label":"Profile","language":"typescript","metadata":{},"qualified_name":"src.api.Profile","source_path":"src/api.ts","span":{"end_column":51,"end_line":1,"start_column":7,"start_line":1}}],"schema_version":1},"imports":[],"markdown_facts":[],"metadata_facts":[{"ecosystem":"typescript_config","field":"compilerOptions.jsx","source_path":"tsconfig.json","value":"react-jsx"},{"ecosystem":"typescript_config","field":"compilerOptions.strict","source_path":"tsconfig.json","value":true},{"ecosystem":"typescript_config","field":"include","source_path":"tsconfig.json","value":["src"]}],"scanner_diagnostics":[]}
